package dev.extframework.mixin.api

public object Opcodes {
    public const val NOP: Int = 0 // visitInsn
    public const val ACONST_NULL: Int = 1 // -
    public const val ICONST_M1: Int = 2 // -
    public const val ICONST_0: Int = 3 // -
    public const val ICONST_1: Int = 4 // -
    public const val ICONST_2: Int = 5 // -
    public const val ICONST_3: Int = 6 // -
    public const val ICONST_4: Int = 7 // -
    public const val ICONST_5: Int = 8 // -
    public const val LCONST_0: Int = 9 // -
    public const val LCONST_1: Int = 10 // -
    public const val FCONST_0: Int = 11 // -
    public const val FCONST_1: Int = 12 // -
    public const val FCONST_2: Int = 13 // -
    public const val DCONST_0: Int = 14 // -
    public const val DCONST_1: Int = 15 // -
    public const val BIPUSH: Int = 16 // visitIntInsn
    public const val SIPUSH: Int = 17 // -
    public const val LDC: Int = 18 // visitLdcInsn
    public const val ILOAD: Int = 21 // visitVarInsn
    public const val LLOAD: Int = 22 // -
    public const val FLOAD: Int = 23 // -
    public const val DLOAD: Int = 24 // -
    public const val ALOAD: Int = 25 // -
    public const val IALOAD: Int = 46 // visitInsn
    public const val LALOAD: Int = 47 // -
    public const val FALOAD: Int = 48 // -
    public const val DALOAD: Int = 49 // -
    public const val AALOAD: Int = 50 // -
    public const val BALOAD: Int = 51 // -
    public const val CALOAD: Int = 52 // -
    public const val SALOAD: Int = 53 // -
    public const val ISTORE: Int = 54 // visitVarInsn
    public const val LSTORE: Int = 55 // -
    public const val FSTORE: Int = 56 // -
    public const val DSTORE: Int = 57 // -
    public const val ASTORE: Int = 58 // -
    public const val IASTORE: Int = 79 // visitInsn
    public const val LASTORE: Int = 80 // -
    public const val FASTORE: Int = 81 // -
    public const val DASTORE: Int = 82 // -
    public const val AASTORE: Int = 83 // -
    public const val BASTORE: Int = 84 // -
    public const val CASTORE: Int = 85 // -
    public const val SASTORE: Int = 86 // -
    public const val POP: Int = 87 // -
    public const val POP2: Int = 88 // -
    public const val DUP: Int = 89 // -
    public const val DUP_X1: Int = 90 // -
    public const val DUP_X2: Int = 91 // -
    public const val DUP2: Int = 92 // -
    public const val DUP2_X1: Int = 93 // -
    public const val DUP2_X2: Int = 94 // -
    public const val SWAP: Int = 95 // -
    public const val IADD: Int = 96 // -
    public const val LADD: Int = 97 // -
    public const val FADD: Int = 98 // -
    public const val DADD: Int = 99 // -
    public const val ISUB: Int = 100 // -
    public const val LSUB: Int = 101 // -
    public const val FSUB: Int = 102 // -
    public const val DSUB: Int = 103 // -
    public const val IMUL: Int = 104 // -
    public const val LMUL: Int = 105 // -
    public const val FMUL: Int = 106 // -
    public const val DMUL: Int = 107 // -
    public const val IDIV: Int = 108 // -
    public const val LDIV: Int = 109 // -
    public const val FDIV: Int = 110 // -
    public const val DDIV: Int = 111 // -
    public const val IREM: Int = 112 // -
    public const val LREM: Int = 113 // -
    public const val FREM: Int = 114 // -
    public const val DREM: Int = 115 // -
    public const val INEG: Int = 116 // -
    public const val LNEG: Int = 117 // -
    public const val FNEG: Int = 118 // -
    public const val DNEG: Int = 119 // -
    public const val ISHL: Int = 120 // -
    public const val LSHL: Int = 121 // -
    public const val ISHR: Int = 122 // -
    public const val LSHR: Int = 123 // -
    public const val IUSHR: Int = 124 // -
    public const val LUSHR: Int = 125 // -
    public const val IAND: Int = 126 // -
    public const val LAND: Int = 127 // -
    public const val IOR: Int = 128 // -
    public const val LOR: Int = 129 // -
    public const val IXOR: Int = 130 // -
    public const val LXOR: Int = 131 // -
    public const val IINC: Int = 132 // visitIincInsn
    public const val I2L: Int = 133 // visitInsn
    public const val I2F: Int = 134 // -
    public const val I2D: Int = 135 // -
    public const val L2I: Int = 136 // -
    public const val L2F: Int = 137 // -
    public const val L2D: Int = 138 // -
    public const val F2I: Int = 139 // -
    public const val F2L: Int = 140 // -
    public const val F2D: Int = 141 // -
    public const val D2I: Int = 142 // -
    public const val D2L: Int = 143 // -
    public const val D2F: Int = 144 // -
    public const val I2B: Int = 145 // -
    public const val I2C: Int = 146 // -
    public const val I2S: Int = 147 // -
    public const val LCMP: Int = 148 // -
    public const val FCMPL: Int = 149 // -
    public const val FCMPG: Int = 150 // -
    public const val DCMPL: Int = 151 // -
    public const val DCMPG: Int = 152 // -
    public const val IFEQ: Int = 153 // visitJumpInsn
    public const val IFNE: Int = 154 // -
    public const val IFLT: Int = 155 // -
    public const val IFGE: Int = 156 // -
    public const val IFGT: Int = 157 // -
    public const val IFLE: Int = 158 // -
    public const val IF_ICMPEQ: Int = 159 // -
    public const val IF_ICMPNE: Int = 160 // -
    public const val IF_ICMPLT: Int = 161 // -
    public const val IF_ICMPGE: Int = 162 // -
    public const val IF_ICMPGT: Int = 163 // -
    public const val IF_ICMPLE: Int = 164 // -
    public const val IF_ACMPEQ: Int = 165 // -
    public const val IF_ACMPNE: Int = 166 // -
    public const val GOTO: Int = 167 // -
    public const val JSR: Int = 168 // -
    public const val RET: Int = 169 // visitVarInsn
    public const val TABLESWITCH: Int = 170 // visiTableSwitchInsn
    public const val LOOKUPSWITCH: Int = 171 // visitLookupSwitch
    public const val IRETURN: Int = 172 // visitInsn
    public const val LRETURN: Int = 173 // -
    public const val FRETURN: Int = 174 // -
    public const val DRETURN: Int = 175 // -
    public const val ARETURN: Int = 176 // -
    public const val RETURN: Int = 177 // -
    public const val GETSTATIC: Int = 178 // visitFieldInsn
    public const val PUTSTATIC: Int = 179 // -
    public const val GETFIELD: Int = 180 // -
    public const val PUTFIELD: Int = 181 // -
    public const val INVOKEVIRTUAL: Int = 182 // visitMethodInsn
    public const val INVOKESPECIAL: Int = 183 // -
    public const val INVOKESTATIC: Int = 184 // -
    public const val INVOKEINTERFACE: Int = 185 // -
    public const val INVOKEDYNAMIC: Int = 186 // visitInvokeDynamicInsn
    public const val NEW: Int = 187 // visitTypeInsn
    public const val NEWARRAY: Int = 188 // visitIntInsn
    public const val ANEWARRAY: Int = 189 // visitTypeInsn
    public const val ARRAYLENGTH: Int = 190 // visitInsn
    public const val ATHROW: Int = 191 // -
    public const val CHECKCAST: Int = 192 // visitTypeInsn
    public const val INSTANCEOF: Int = 193 // -
    public const val MONITORENTER: Int = 194 // visitInsn
    public const val MONITOREXIT: Int = 195 // -
    public const val MULTIANEWARRAY: Int = 197 // visitMultiANewArrayInsn
    public const val IFNULL: Int = 198 // visitJumpInsn
    public const val IFNONNULL: Int = 199 // -
}